{
  "message_id": "4c333c78-e2a4-41fa-8aa7-5b8efea601dd",
  "timestamp": 1770910742.0663044,
  "frame_id": 376,
  "sensor_id": "PHOENIX_RADAR_01",
  "tracks": [
    {
      "track_id": 4,
      "range_m": 221.17329160242429,
      "azimuth_deg": 252.0,
      "radial_velocity_m_s": -3.759245246840334,
      "track_quality": 0.5,
      "track_age_frames": 0,
      "last_update_timestamp": 1770910742.066221,
      "radial_acceleration_m_s2": -0.0010721513991041026
    },
    {
      "track_id": 5,
      "range_m": 232.73566607886332,
      "azimuth_deg": 252.0,
      "radial_velocity_m_s": 3.7005070398584543,
      "track_quality": 0.5,
      "track_age_frames": 0,
      "last_update_timestamp": 1770910742.066259,
      "radial_acceleration_m_s2": 0.0010553990334923064
    }
  ],
  "threat_assessments": [
    {
      "track_id": 4,
      "threat_class": "NEUTRAL",
      "target_type": "UNKNOWN",
      "classification_confidence": 0.25449612736701965,
      "threat_priority": 2,
      "engagement_recommendation": "IGNORE",
      "classification_uncertainty": 0.7455038726329803,
      "position_uncertainty_m": 5.0,
      "velocity_uncertainty_m_s": 2.5
    },
    {
      "track_id": 5,
      "threat_class": "NEUTRAL",
      "target_type": "UNKNOWN",
      "classification_confidence": 0.25449272990226746,
      "threat_priority": 2,
      "engagement_recommendation": "IGNORE",
      "classification_uncertainty": 0.7455072700977325,
      "position_uncertainty_m": 5.0,
      "velocity_uncertainty_m_s": 2.5
    }
  ],
  "scene_context": {
    "scene_type": "SPARSE",
    "clutter_ratio": 0.0,
    "mean_snr_db": -66.88716573338189,
    "num_confirmed_tracks": 2
  }
}