{
  "message_id": "92785ae3-e40e-474e-b934-3f030e60e082",
  "timestamp": 1770913433.8473668,
  "frame_id": 289,
  "sensor_id": "PHOENIX_RADAR_01",
  "tracks": [
    {
      "track_id": 2,
      "range_m": 293.1164974040133,
      "azimuth_deg": 0.0,
      "radial_velocity_m_s": 2.312710795720615,
      "track_quality": 0.5,
      "track_age_frames": 0,
      "last_update_timestamp": 1770913433.8473053,
      "radial_acceleration_m_s2": 0.0012735924230083955
    }
  ],
  "threat_assessments": [
    {
      "track_id": 2,
      "threat_class": "NEUTRAL",
      "target_type": "UNKNOWN",
      "classification_confidence": 0.28732702136039734,
      "threat_priority": 2,
      "engagement_recommendation": "IGNORE",
      "classification_uncertainty": 0.7126729786396027,
      "position_uncertainty_m": 5.0,
      "velocity_uncertainty_m_s": 2.5
    }
  ],
  "scene_context": {
    "scene_type": "SPARSE",
    "clutter_ratio": 0.0,
    "mean_snr_db": -58.22665599102346,
    "num_confirmed_tracks": 1
  }
}