{
  "message_id": "3a4e9954-44a0-4341-bcfa-da9d2eebe955",
  "timestamp": 1770912351.6952963,
  "frame_id": 372,
  "sensor_id": "PHOENIX_RADAR_01",
  "tracks": [
    {
      "track_id": 4,
      "range_m": 222.6769039290485,
      "azimuth_deg": 108.0,
      "radial_velocity_m_s": -3.758816386280693,
      "track_quality": 0.5,
      "track_age_frames": 0,
      "last_update_timestamp": 1770912351.695158,
      "radial_acceleration_m_s2": -0.0010721513991041026
    },
    {
      "track_id": 5,
      "range_m": 231.2555476948427,
      "azimuth_deg": 108.0,
      "radial_velocity_m_s": 3.7000848802450577,
      "track_quality": 0.5,
      "track_age_frames": 0,
      "last_update_timestamp": 1770912351.6952572,
      "radial_acceleration_m_s2": 0.0010553990334923064
    }
  ],
  "threat_assessments": [
    {
      "track_id": 4,
      "threat_class": "NEUTRAL",
      "target_type": "UNKNOWN",
      "classification_confidence": 0.3057985007762909,
      "threat_priority": 2,
      "engagement_recommendation": "IGNORE",
      "classification_uncertainty": 0.6942014992237091,
      "position_uncertainty_m": 5.0,
      "velocity_uncertainty_m_s": 2.5
    },
    {
      "track_id": 5,
      "threat_class": "NEUTRAL",
      "target_type": "UNKNOWN",
      "classification_confidence": 0.3057841360569,
      "threat_priority": 2,
      "engagement_recommendation": "IGNORE",
      "classification_uncertainty": 0.6942158639431,
      "position_uncertainty_m": 5.0,
      "velocity_uncertainty_m_s": 2.5
    }
  ],
  "scene_context": {
    "scene_type": "SPARSE",
    "clutter_ratio": 0.0,
    "mean_snr_db": -96.76582831337828,
    "num_confirmed_tracks": 2
  }
}